jpy_sql_generator/__init__.py
jpy_sql_generator/cli.py
jpy_sql_generator/code_generator.py
jpy_sql_generator/sql_helper.py
jpy_sql_generator/sql_parser.py
jpy_sql_generator/templates/python_class.j2
jpy_sql_generator-0.2.4.dist-info/licenses/LICENSE
jpy_sql_generator-0.2.4.dist-info/METADATA
jpy_sql_generator-0.2.4.dist-info/WHEEL
jpy_sql_generator-0.2.4.dist-info/entry_points.txt
jpy_sql_generator-0.2.4.dist-info/top_level.txt
jpy_sql_generator-0.2.4.dist-info/RECORD
